helstrom/__init__.py
helstrom/__main__.py
helstrom/helstromSDP.py
helstrom-0.3.dist-info/LICENSE.md
helstrom-0.3.dist-info/METADATA
helstrom-0.3.dist-info/WHEEL
helstrom-0.3.dist-info/entry_points.txt
helstrom-0.3.dist-info/top_level.txt
helstrom-0.3.dist-info/RECORD
