Metadata-Version: 2.1
Name: helstrom
Version: 0.3
Summary: A quantum state distinguisher with minimum theoretical worst-case probability of error.
Home-page: https://github.com/benedictusalvian/helstrom
Author: Benedictus Alvian Sofjan
Author-email: benedictus.sofjan@gmail.com
License: MIT
Keywords: python,quantum,quantum-computing,quantum-information,quantum-theory,helstrom,distinguisher
Platform: UNKNOWN
Classifier: Development Status :: 3 - Alpha
Classifier: License :: OSI Approved :: MIT License
Classifier: Programming Language :: Python :: 3
Classifier: Programming Language :: Python :: 3.8
Classifier: Programming Language :: Python :: 3.9
Classifier: Operating System :: OS Independent
Requires-Dist: cvxpy (>=1.1.12)
Requires-Dist: Mosek (>=9.2.43)
Requires-Dist: numpy (>=1.20.0)
